{
	"install": "messages/install.org",
	"1.0.0": "messages/install.org",
	"1.0.1": "messages/1.0.1.org",
	"1.0.2": "messages/1.0.2.org",
	"1.0.3": "messages/1.0.3.org",
	"1.0.4": "messages/1.0.4.org",
	"1.0.5": "messages/1.0.5.org",
	"1.0.6": "messages/1.0.6.org",
	"1.0.7": "messages/1.0.7.org",
	"1.0.8": "messages/1.0.8.org",
	"1.0.9": "messages/1.0.9.org",
	"1.0.10": "messages/1.0.10.org",
	"1.1.0": "messages/1.1.0.org",
	"1.1.1": "messages/1.1.1.org",
	"1.1.2": "messages/1.1.2.org",
	"1.1.3": "messages/1.1.3.org",
	"1.1.4": "messages/1.1.4.org",
	"1.1.5": "messages/1.1.5.org",
	"1.1.6": "messages/1.1.6.org",
	"1.1.7": "messages/1.1.7.org",
	"1.1.8": "messages/1.1.8.org",
	"1.1.9": "messages/1.1.9.org",
	"1.1.10": "messages/1.1.10.org",
	"1.1.11": "messages/1.1.11.org",
	"1.1.12": "messages/1.1.12.org",
	"1.1.13": "messages/1.1.13.org",
	"1.1.14": "messages/1.1.14.org",
	"1.1.15": "messages/1.1.15.org",
	"1.1.16": "messages/1.1.16.org",
	"1.1.17": "messages/1.1.17.org",
	"1.1.18": "messages/1.1.18.org",
	"1.1.19": "messages/1.1.19.org",
	"1.1.20": "messages/1.1.20.org",
	"1.1.21": "messages/1.1.21.org",
	"1.1.22": "messages/1.1.22.org",
	"1.1.23": "messages/1.1.23.org",
	"1.1.24": "messages/1.1.24.org",
	"1.1.25": "messages/1.1.25.org",
	"1.1.26": "messages/1.1.26.org",
	"1.1.27": "messages/1.1.27.org",
	"1.1.28": "messages/1.1.28.org",
	"1.1.29": "messages/1.1.29.org",
	"1.1.30": "messages/1.1.30.org",
	"1.2.0": "messages/1.2.0.org",
	"1.2.1": "messages/1.2.1.org",
	"1.2.2": "messages/1.2.2.org",
	"1.2.3": "messages/1.2.3.org",
	"1.2.4": "messages/1.2.4.org",
	"1.2.5": "messages/1.2.5.org",
	"1.2.6": "messages/1.2.6.org",
	"1.2.7": "messages/1.2.7.org",
	"1.2.8": "messages/1.2.8.org",
	"1.2.9": "messages/1.2.9.org",
	"1.2.10": "messages/1.2.10.org",
	"1.2.11": "messages/1.2.11.org",
	"1.2.12": "messages/1.2.12.org",
	"1.2.13": "messages/1.2.13.org",
	"1.2.14": "messages/1.2.14.org",
	"1.2.15": "messages/1.2.15.org",
	"1.2.16": "messages/1.2.16.org",
	"1.2.17": "messages/1.2.17.org",
	"1.2.18": "messages/1.2.18.org",
	"1.2.19": "messages/1.2.19.org",
	"1.2.20": "messages/1.2.20.org",
	"1.2.21": "messages/1.2.21.org",
	"1.2.22": "messages/1.2.22.org",
	"1.2.23": "messages/1.2.23.org",
	"1.2.24": "messages/1.2.24.org",
	"1.2.25": "messages/1.2.25.org",
	"1.2.26": "messages/1.2.26.org",
	"1.2.27": "messages/1.2.27.org",
	"1.2.28": "messages/1.2.28.org",
	"1.2.29": "messages/1.2.29.org",
	"1.2.30": "messages/1.2.30.org",
	"1.2.31": "messages/1.2.31.org",
	"1.2.32": "messages/1.2.32.org",
	"1.2.33": "messages/1.2.33.org",
	"1.2.34": "messages/1.2.34.org",
	"1.2.35": "messages/1.2.35.org",
	"1.2.36": "messages/1.2.36.org",
	"1.2.37": "messages/1.2.37.org",
	"1.2.38": "messages/1.2.38.org",
	"1.2.39": "messages/1.2.39.org",
	"1.2.40": "messages/1.2.40.org",
	"1.2.41": "messages/1.2.41.org",
	"1.2.42": "messages/1.2.42.org",
	"1.2.43": "messages/1.2.43.org",
	"1.2.44": "messages/1.2.44.org",
	"1.2.45": "messages/1.2.45.org",
	"1.2.46": "messages/1.2.46.org",
	"1.2.47": "messages/1.2.47.org",
	"1.2.48": "messages/1.2.48.org",
	"1.2.49": "messages/1.2.49.org",
	"1.2.50": "messages/1.2.50.org",
	"1.2.51": "messages/1.2.51.org",
	"1.2.52": "messages/1.2.52.org",
	"1.2.53": "messages/1.2.53.org",
	"1.2.54": "messages/1.2.54.org"
}